spos/__init__.py
spos/blocks.py
spos/checks.py
spos/command.py
spos/exceptions.py
spos/random.py
spos/typing.py
spos/utils.py
spos-1.6.0b0.data/scripts/spos
test/__init__.py
test/test_bin.py
test/test_block.py
test/test_command.py
test/test_random.py
test/test_spos.py
spos-1.6.0b0.dist-info/LICENSE.md
spos-1.6.0b0.dist-info/METADATA
spos-1.6.0b0.dist-info/WHEEL
spos-1.6.0b0.dist-info/top_level.txt
spos-1.6.0b0.dist-info/RECORD
