Metadata-Version: 2.1
Name: spos
Version: 1.6.0b0
Summary: SPOS stands for Small Payload Object Serializer
Home-page: https://github.com/luxedo/SPOS
Author: Luiz Eduardo Amaral
Author-email: luizamaral306@gmail.com
License: LICENSE.md
Keywords: serializer LoRa Globalstar low-bandwidth
Classifier: Development Status :: 3 - Alpha
Classifier: Intended Audience :: Developers
Classifier: Topic :: Software Development :: Build Tools
Classifier: License :: OSI Approved :: GNU General Public License v3 (GPLv3)
Classifier: Operating System :: POSIX :: Linux
Classifier: Programming Language :: Python :: 3.7
Classifier: Programming Language :: Python :: 3.8
Requires-Python: >=3.7
License-File: LICENSE.md
Requires-Dist: crc8 (==0.1.0)
